prepstack/__init__.py
prepstack/helpers.py
prepstack/cleaning/__init__.py
prepstack/cleaning/basic.py
prepstack/cleaning/duplicates.py
prepstack/cleaning/missing.py
prepstack/cleaning/outliers.py
prepstack/cleaning/types.py
prepstack/explore/__init__.py
prepstack/explore/correlations.py
prepstack/explore/distributions.py
prepstack/explore/missing.py
prepstack/explore/overview.py
prepstack/explore/profiling.py
prepstack/model/__init__.py
prepstack/model/core.py
prepstack/model_prep/class_balance.py
prepstack/model_prep/feature_selection.py
prepstack/model_prep/init.py
prepstack/model_prep/splits.py
prepstack/model_prep/evaluation/__init__.py
prepstack/model_prep/evaluation/classification.py
prepstack/model_prep/evaluation/regression.py
prepstack/model_prep/evaluation/summary.py
prepstack/model_prep/training/__init__.py
prepstack/model_prep/training/baseline.py
prepstack/model_prep/training/fit.py
prepstack/model_prep/training/predict.py
prepstack/model_prep/validation/__init__.py
prepstack/model_prep/validation/core.py
prepstack/transform/columns/binning.py
prepstack/transform/columns/date_ops.py
prepstack/transform/columns/encoding.py
prepstack/transform/columns/feature_creation.py
prepstack/transform/columns/init.py
prepstack/transform/columns/rename.py
prepstack/transform/columns/scaling.py
prepstack/transform/columns/string_ops.py
prepstack/transform/diagnostics/merge_diagnostics.py
prepstack/transform/joins/__init__.py
prepstack/transform/joins/inner_join.py
prepstack/transform/joins/left_join.py
prepstack/transform/joins/outer_join.py
prepstack/transform/joins/right_join.py
prepstack/transform/joins/smart_merge.py
prepstack/transform/missing/__init__.py
prepstack/transform/missing/categorical_impute.py
prepstack/transform/missing/mixed_impute.py
prepstack/transform/missing/numeric_impute.py
prepstack/transform/rows/dedupe.py
prepstack/transform/rows/filter.py
prepstack/transform/rows/index_ops.py
prepstack/transform/rows/init.py
prepstack-0.1.0.dist-info/METADATA
prepstack-0.1.0.dist-info/WHEEL
prepstack-0.1.0.dist-info/top_level.txt
prepstack-0.1.0.dist-info/RECORD
