Metadata-Version: 2.4
Name: prepstack
Version: 0.1.0
Summary: Modular data analysis and ML workflow toolkit
Author: Ridhisha Tyagi
Project-URL: Homepage, https://github.com/ridhisha-tyagi/prepstack
Requires-Python: >=3.9
Requires-Dist: pandas
Requires-Dist: numpy
Requires-Dist: scikit-learn
Requires-Dist: imbalanced-learn
